daisykit/__init__.py
daisykit/daisykit.cp37-win_amd64.pyd
daisykit/opencv_world470.dll
daisykit/utils/__init__.py
daisykit/utils/asset_store.py
daisykit/utils/conversion.py
daisykit/utils/download.py
daisykit/utils/generate_file_list.py
daisykit-0.3.0.5.dist-info/LICENSE
daisykit-0.3.0.5.dist-info/METADATA
daisykit-0.3.0.5.dist-info/WHEEL
daisykit-0.3.0.5.dist-info/top_level.txt
daisykit-0.3.0.5.dist-info/RECORD
