Metadata-Version: 2.1
Name: daisykit
Version: 0.3.0.5
Summary: Deploy AI Systems Yourself (DAISY) Kit. DaisyKit Python is the wrapper of DaisyKit SDK, an easy AI framework for everyone.
Home-page: https://daisykit.nrl.ai/
Author: DaisyKit Team - Neural Research Lab
Author-email: daisykit@nrl.ai
Maintainer: DaisyKit Team - Neural Research Lab
Maintainer-email: daisykit@nrl.ai
License: Apache License 2.0
Classifier: Programming Language :: C++
Classifier: Programming Language :: Python :: 3
Classifier: Programming Language :: Python :: 3.6
Classifier: Programming Language :: Python :: 3.7
Classifier: Programming Language :: Python :: 3.8
Classifier: Programming Language :: Python :: 3.9
Classifier: Programming Language :: Python :: 3.10
Classifier: License :: OSI Approved :: Apache Software License
Classifier: Operating System :: OS Independent
Requires-Python: >=3.6
License-File: LICENSE
Requires-Dist: numpy
Requires-Dist: tqdm
Requires-Dist: requests
Requires-Dist: portalocker
Requires-Dist: opencv-python
